vegetarian_cookbook/__init__.py
vegetarian_cookbook/admin.py
vegetarian_cookbook/apps.py
vegetarian_cookbook/appsettings.py
vegetarian_cookbook/forms.py
vegetarian_cookbook/lookups.py
vegetarian_cookbook/models.py
vegetarian_cookbook/search.py
vegetarian_cookbook/tests.py
vegetarian_cookbook/tests_models.py
vegetarian_cookbook/translit.py
vegetarian_cookbook/urls.py
vegetarian_cookbook/views.py
vegetarian_cookbook/migrations/0001_initial.py
vegetarian_cookbook/migrations/0002_auto_20180320_1123.py
vegetarian_cookbook/migrations/0003_category_image.py
vegetarian_cookbook/migrations/0004_auto_20180320_1441.py
vegetarian_cookbook/migrations/0005_auto_20180321_1723.py
vegetarian_cookbook/migrations/0006_tag_counter.py
vegetarian_cookbook/migrations/0007_auto_20180412_1011.py
vegetarian_cookbook/migrations/0008_auto_20180412_1018.py
vegetarian_cookbook/migrations/0009_auto_20180412_1239.py
vegetarian_cookbook/migrations/0010_auto_20180413_1747.py
vegetarian_cookbook/migrations/0011_ingredientnutritionalvalue_unit.py
vegetarian_cookbook/migrations/0012_auto_20180529_0956.py
vegetarian_cookbook/migrations/0013_auto_20180529_1008.py
vegetarian_cookbook/migrations/0014_auto_20180529_1013.py
vegetarian_cookbook/migrations/0015_auto_20180605_0934.py
vegetarian_cookbook/migrations/0016_auto_20180607_1049.py
vegetarian_cookbook/migrations/0017_auto_20180615_0821.py
vegetarian_cookbook/migrations/__init__.py
vegetarian_cookbook/static/vegetarian_cookbook/css/jquery-ui.css
vegetarian_cookbook/static/vegetarian_cookbook/css/style.css
vegetarian_cookbook/static/vegetarian_cookbook/img/default.jpg
vegetarian_cookbook/static/vegetarian_cookbook/img/edit.png
vegetarian_cookbook/static/vegetarian_cookbook/img/icon_complexity.png
vegetarian_cookbook/static/vegetarian_cookbook/jqcloud/LICENSE.txt
vegetarian_cookbook/static/vegetarian_cookbook/jqcloud/README.md
vegetarian_cookbook/static/vegetarian_cookbook/jqcloud/jqcloud-1.0.4.js
django_vegetarian_cookbook-1.0.9.dist-info/LICENSE
django_vegetarian_cookbook-1.0.9.dist-info/METADATA
django_vegetarian_cookbook-1.0.9.dist-info/WHEEL
django_vegetarian_cookbook-1.0.9.dist-info/top_level.txt
django_vegetarian_cookbook-1.0.9.dist-info/RECORD
