Metadata-Version: 2.1
Name: django-vegetarian-cookbook
Version: 1.0.9
Summary: Django application for the publication of vegetarian culinary recipes with the calculation of energy and nutrients.
Home-page: https://github.com/sergey-panasenko/django-vegetarian-cookbook
Author: Sergey Panasenko
Author-email: sergey.panasenko@gmail.com
License: AGPL v3
Platform: UNKNOWN
Requires-Dist: Django (>=2.0.11)
Requires-Dist: django-appconf
Requires-Dist: django-bootstrap4
Requires-Dist: django-ckeditor
Requires-Dist: django-imagekit
Requires-Dist: django-js-asset
Requires-Dist: mysqlclient
Requires-Dist: pilkit
Requires-Dist: Pillow
Requires-Dist: pytz
Requires-Dist: six
Requires-Dist: sqlparse
Requires-Dist: django-ajaximage
